{
  "id": "csb-exalted2e-module",
  "title": "CSB Exalted 2e Module",
  "version": "1.1.0",
  "compatibility": {
    "minimum": "10",
    "verified": "11"
  },
  "relationships": {
    "systems": [
      {
        "id": "custom-system-builder",
        "type": "system",
        "compatibility": {}
      }
    ]
  },
  "authors": [
    {
      "name": "Duergar85",
      "flags": {}
    }
  ],
  "styles": [
	  "css/csb-exalted2e-module.css"
  ],
  "esmodules": [
	  "js/csb-exalted2e-module.js",
	  "js/WWHealthCounter.js"
  ]
}